pyassist_linux/__init__.py
pyassist_linux/device_utils.py
pyassist_linux/grep_utils.py
pyassist_linux/process_utils.py
pyassist_linux-0.1.1.dist-info/LICENSE
pyassist_linux-0.1.1.dist-info/METADATA
pyassist_linux-0.1.1.dist-info/WHEEL
pyassist_linux-0.1.1.dist-info/top_level.txt
pyassist_linux-0.1.1.dist-info/RECORD
