Metadata-Version: 2.1
Name: pyassist-linux
Version: 0.1.1
Summary: This is Python Utility for linux
Home-page: https://github.com/ISabariRajan
Download-URL: https://github.com/ISabariRajan/LinuxUtilities/archive/refs/tags/v-0.1.1.tar.gz
Author: Sabari Rajan
Author-email: mailme@isbarirajan.com
License: MIT
Keywords: Utility,utils,pyutils,assist,easy,service
Classifier: Development Status :: 3 - Alpha
Classifier: Intended Audience :: Developers
Classifier: Topic :: Software Development :: Build Tools
Classifier: License :: OSI Approved :: MIT License
Classifier: Programming Language :: Python :: 3
Classifier: Programming Language :: Python :: 3.4
Classifier: Programming Language :: Python :: 3.5
Classifier: Programming Language :: Python :: 3.6
License-File: LICENSE
Requires-Dist: pyassist
